<?xml version="1.0" encoding="utf-8" standalone="yes"?>

<news>
	<thmbimg>news/1.jpg</thmbimg>
	<heading>Flash Flash Flash !!!</heading>
	<date>10/10/2008 22:22</date>
	<subject><![CDATA[<font color="#FFCCDD"><b>HTML Code Support Here</b> </font>Lorem ipsum dolor sit amet, consectetur adipisicing elit, sed do eiusmod tempor incididunt ut labore et dolore magna aliqua. Ut enim ad minim veniam, quis nostrud exercitation ullamco laboris nisi ut aliquip ex ea commodo consequat.Duis aute irure dolor in reprehenderit in voluptate velit esse cillum dolore eu fugiat nulla pariatur.Lorem ipsum dolor sit amet, consectetur adipisicing elit, sed do eiusmod tempor incididunt ut labore et dolore magna aliqua. Ut enim ad minim veniam, quis nostrud exercitation ullamco laboris nisi ut aliquip ex ea commodo consequat.]]></subject>
</news>

<news>
	<thmbimg>news/2.jpg</thmbimg>
	<heading>Heading 1</heading>
	<date>10/10/2008 22:22</date>
	<subject><![CDATA[<font color="#22FFEE"><b>HTML Code Support Here</b> </font>Lorem ipsum dolor sit amet, consectetur adipisicing elit, sed do eiusmod tempor incididunt ut labore et dolore magna aliqua. Ut enim ad minim veniam, quis nostrud exercitation ullamco laboris nisi ut aliquip ex ea commodo consequat.Duis aute irure dolor in reprehenderit in voluptate velit esse cillum dolore eu fugiat nulla pariatur.Lorem ipsum dolor sit amet, consectetur adipisicing elit, sed do eiusmod tempor incididunt ut labore et dolore magna aliqua. Ut enim ad minim veniam, quis nostrud exercitation ullamco laboris nisi ut aliquip ex ea commodo consequat.]]></subject>
</news>

<news>
	<thmbimg>news/3.jpg</thmbimg>
	<heading>Flash Flash Flash !!!</heading>
	<date>10/10/2008 22:22</date>
	<subject><![CDATA[<font color="#FFCCDD"><b>HTML Code Support Here</b> </font>Lorem ipsum dolor sit amet, consectetur adipisicing elit, sed do eiusmod tempor incididunt ut labore et dolore magna aliqua. Ut enim ad minim veniam, quis nostrud exercitation ullamco laboris nisi ut aliquip ex ea commodo consequat.Duis aute irure dolor in reprehenderit in voluptate velit esse cillum dolore eu fugiat nulla pariatur.Lorem ipsum dolor sit amet, consectetur adipisicing elit, sed do eiusmod tempor incididunt ut labore et dolore magna aliqua. Ut enim ad minim veniam, quis nostrud exercitation ullamco laboris nisi ut aliquip ex ea commodo consequat.]]></subject>
</news>

<news>
	<thmbimg>news/1.jpg</thmbimg>
	<heading>Heading 1</heading>
	<date>10/10/2008 22:22</date>
	<subject><![CDATA[<font color="#22FFEE"><b>HTML Code Support Here</b> </font>Lorem ipsum dolor sit amet, consectetur adipisicing elit, sed do eiusmod tempor incididunt ut labore et dolore magna aliqua. Ut enim ad minim veniam, quis nostrud exercitation ullamco laboris nisi ut aliquip ex ea commodo consequat.Duis aute irure dolor in reprehenderit in voluptate velit esse cillum dolore eu fugiat nulla pariatur.Lorem ipsum dolor sit amet, consectetur adipisicing elit, sed do eiusmod tempor incididunt ut labore et dolore magna aliqua. Ut enim ad minim veniam, quis nostrud exercitation ullamco laboris nisi ut aliquip ex ea commodo consequat.]]></subject>
</news>

<news>
	<thmbimg>news/2.jpg</thmbimg>
	<heading>Flash Flash Flash !!!</heading>
	<date>10/10/2008 22:22</date>
	<subject><![CDATA[<font color="#FFCCDD"><b>HTML Code Support Here</b> </font>Lorem ipsum dolor sit amet, consectetur adipisicing elit, sed do eiusmod tempor incididunt ut labore et dolore magna aliqua. Ut enim ad minim veniam, quis nostrud exercitation ullamco laboris nisi ut aliquip ex ea commodo consequat.Duis aute irure dolor in reprehenderit in voluptate velit esse cillum dolore eu fugiat nulla pariatur.Lorem ipsum dolor sit amet, consectetur adipisicing elit, sed do eiusmod tempor incididunt ut labore et dolore magna aliqua. Ut enim ad minim veniam, quis nostrud exercitation ullamco laboris nisi ut aliquip ex ea commodo consequat.]]></subject>
</news>

<news>
	<thmbimg>news/3.jpg</thmbimg>
	<heading>Heading 1</heading>
	<date>10/10/2008 22:22</date>
	<subject><![CDATA[<font color="#22FFEE"><b>HTML Code Support Here</b> </font>Lorem ipsum dolor sit amet, consectetur adipisicing elit, sed do eiusmod tempor incididunt ut labore et dolore magna aliqua. Ut enim ad minim veniam, quis nostrud exercitation ullamco laboris nisi ut aliquip ex ea commodo consequat.Duis aute irure dolor in reprehenderit in voluptate velit esse cillum dolore eu fugiat nulla pariatur.Lorem ipsum dolor sit amet, consectetur adipisicing elit, sed do eiusmod tempor incididunt ut labore et dolore magna aliqua. Ut enim ad minim veniam, quis nostrud exercitation ullamco laboris nisi ut aliquip ex ea commodo consequat.]]></subject>
</news>